auth_mixins/__init__.py
django_auth_mixins-1.0.1.dist-info/DESCRIPTION.rst
django_auth_mixins-1.0.1.dist-info/METADATA
django_auth_mixins-1.0.1.dist-info/RECORD
django_auth_mixins-1.0.1.dist-info/WHEEL
django_auth_mixins-1.0.1.dist-info/metadata.json
django_auth_mixins-1.0.1.dist-info/top_level.txt
