Metadata-Version: 1.1
Name: django-auth-mixins
Version: 1.0.1
Summary: Backport of Django 1.9 auth mixins.
Home-page: https://github.com/dbrgn/django-auth-mixins/
Author: Danilo Bargen
Author-email: mail@dbrgn.ch
License: BSD
Keywords: django mixins backport backports 1.8 1.9 auth
Platform: UNKNOWN
Classifier: Development Status :: 4 - Beta
Classifier: Framework :: Django
Classifier: Framework :: Django :: 1.8
Classifier: License :: OSI Approved :: BSD License
Classifier: Programming Language :: Python :: 2
Classifier: Programming Language :: Python :: 3
